{
	"name": "spotify_pipeline",
	"properties": {
		"activities": [
			{
				"name": "AzureSQL2Lake",
				"type": "Copy",
				"dependsOn": [
					{
						"activity": "last_cdc",
						"dependencyConditions": [
							"Succeeded"
						]
					},
					{
						"activity": "Set variable1",
						"dependencyConditions": [
							"Succeeded"
						]
					}
				],
				"policy": {
					"timeout": "0.12:00:00",
					"retry": 0,
					"retryIntervalInSeconds": 30,
					"secureOutput": false,
					"secureInput": false
				},
				"userProperties": [],
				"typeProperties": {
					"source": {
						"type": "SqlServerSource",
						"sqlReaderQuery": {
							"value": "SELECT * FROM @{pipeline().parameters.schema}.@{pipeline().parameters.table} \nWHERE @{pipeline().parameters.cdc_col} > '@{activity('last_cdc').output.value}'",
							"type": "Expression"
						},
						"queryTimeout": "02:00:00",
						"partitionOption": "None"
					},
					"sink": {
						"type": "ParquetSink",
						"storeSettings": {
							"type": "AzureBlobFSWriteSettings"
						},
						"formatSettings": {
							"type": "ParquetWriteSettings"
						}
					},
					"enableStaging": false,
					"translator": {
						"type": "TabularTranslator",
						"typeConversion": true,
						"typeConversionSettings": {
							"allowDataTruncation": true,
							"treatBooleanAsNumber": false
						}
					}
				},
				"inputs": [
					{
						"referenceName": "spotify_sql_source",
						"type": "DatasetReference"
					}
				],
				"outputs": [
					{
						"referenceName": "Parquet_spotify_sink",
						"type": "DatasetReference",
						"parameters": {
							"container": "bronze",
							"folder": "users",
							"file": {
								"value": "@concat(pipeline().parameters.table,'_', variables('current_time'))",
								"type": "Expression"
							}
						}
					}
				]
			},
			{
				"name": "last_cdc",
				"type": "Lookup",
				"dependsOn": [],
				"policy": {
					"timeout": "0.12:00:00",
					"retry": 0,
					"retryIntervalInSeconds": 30,
					"secureOutput": false,
					"secureInput": false
				},
				"userProperties": [],
				"typeProperties": {
					"source": {
						"type": "JsonSource",
						"storeSettings": {
							"type": "AzureBlobFSReadSettings",
							"recursive": true,
							"enablePartitionDiscovery": false
						},
						"formatSettings": {
							"type": "JsonReadSettings"
						}
					},
					"dataset": {
						"referenceName": "empty_json_spotify",
						"type": "DatasetReference",
						"parameters": {
							"container": "bronze",
							"folder": "cdc"
						}
					},
					"firstRowOnly": false
				}
			},
			{
				"name": "Set variable1",
				"type": "SetVariable",
				"dependsOn": [],
				"policy": {
					"secureOutput": false,
					"secureInput": false
				},
				"userProperties": [],
				"typeProperties": {
					"variableName": "current_time",
					"value": {
						"value": "@utcNow()",
						"type": "Expression"
					}
				}
			}
		],
		"parameters": {
			"schema": {
				"type": "string"
			},
			"table": {
				"type": "string"
			},
			"cdc_col": {
				"type": "string"
			}
		},
		"variables": {
			"current_time": {
				"type": "String"
			}
		},
		"folder": {
			"name": "spotify-project-ansh"
		},
		"annotations": []
	}
}